splitflap/__init__.py
splitflap/exceptions.py
splitflap/metadata.py
splitflap/display/__init__.py
splitflap/display/ascii_graphics.py
splitflap/display/display.py
splitflap/display/fields.py
splitflap/krone/__init__.py
splitflap/krone/fbm.py
splitflap/krone/hlst.py
splitflap/krone/k8200.py
splitflap/omega/__init__.py
splitflap/omega/rs485.py
pySplitFlap-1.2.0.dist-info/LICENSE
pySplitFlap-1.2.0.dist-info/METADATA
pySplitFlap-1.2.0.dist-info/WHEEL
pySplitFlap-1.2.0.dist-info/top_level.txt
pySplitFlap-1.2.0.dist-info/RECORD
