Metadata-Version: 2.1
Name: pySplitFlap
Version: 1.2.0
Summary: A library for controlling split-flap displays
Home-page: https://github.com/Mezgrman/pySplitFlap
Author: Julian Metzler
Author-email: git@mezgr.de
License: GPLv3
Keywords: sign message board library wrapper serial text display train
Platform: UNKNOWN
Requires-Dist: pyserial
